django_rest_framework_mango/__init__.py
django_rest_framework_mango/middlewares.py
django_rest_framework_mango/mixins.py
djangorestframework_mango-0.2.0.dist-info/LICENSE
djangorestframework_mango-0.2.0.dist-info/METADATA
djangorestframework_mango-0.2.0.dist-info/WHEEL
djangorestframework_mango-0.2.0.dist-info/top_level.txt
djangorestframework_mango-0.2.0.dist-info/RECORD
