Metadata-Version: 2.1
Name: djangorestframework-mango
Version: 0.2.0
Summary: A set of viewset mixin for the Django REST Framework.
Home-page: https://github.com/legshort/django-rest-framework-mango/
Author: Jun Young Lee
Author-email: legshort@gmail.com
License: MIT
Keywords: djangorestframework,drf,util,viewset
Platform: UNKNOWN
Classifier: License :: OSI Approved :: MIT License
Classifier: Programming Language :: Python :: 3
Requires-Dist: django
Requires-Dist: djangorestframework
